skill_ovos_soundcloud/LICENSE.md
skill_ovos_soundcloud/MANIFEST.in
skill_ovos_soundcloud/README.md
skill_ovos_soundcloud/__init__.py
skill_ovos_soundcloud/version.py
skill_ovos_soundcloud/locale/de-de/soundcloud.voc
skill_ovos_soundcloud/locale/de-de/soundcloud_skill.voc
skill_ovos_soundcloud/locale/en-us/skill.json
skill_ovos_soundcloud/locale/en-us/soundcloud.voc
skill_ovos_soundcloud/locale/en-us/soundcloud_skill.voc
skill_ovos_soundcloud/locale/es-es/soundcloud.voc
skill_ovos_soundcloud/locale/es-es/soundcloud_skill.voc
skill_ovos_soundcloud/locale/eu/soundcloud.voc
skill_ovos_soundcloud/locale/fr-fr/soundcloud.voc
skill_ovos_soundcloud/locale/fr-fr/soundcloud_skill.voc
skill_ovos_soundcloud/locale/gl-es/soundcloud.voc
skill_ovos_soundcloud/locale/it-it/soundcloud.voc
skill_ovos_soundcloud/locale/it-it/soundcloud_skill.voc
skill_ovos_soundcloud/locale/pt-pt/soundcloud.voc
skill_ovos_soundcloud/locale/pt-pt/soundcloud_skill.voc
skill_ovos_soundcloud/skill_soundcloud.egg-info/PKG-INFO
skill_ovos_soundcloud/skill_soundcloud.egg-info/SOURCES.txt
skill_ovos_soundcloud/skill_soundcloud.egg-info/dependency_links.txt
skill_ovos_soundcloud/skill_soundcloud.egg-info/entry_points.txt
skill_ovos_soundcloud/skill_soundcloud.egg-info/requires.txt
skill_ovos_soundcloud/skill_soundcloud.egg-info/top_level.txt
skill_soundcloud-0.1.5.dist-info/LICENSE.md
skill_soundcloud-0.1.5.dist-info/METADATA
skill_soundcloud-0.1.5.dist-info/WHEEL
skill_soundcloud-0.1.5.dist-info/entry_points.txt
skill_soundcloud-0.1.5.dist-info/top_level.txt
skill_soundcloud-0.1.5.dist-info/RECORD
