Metadata-Version: 2.1
Name: skill-soundcloud
Version: 0.1.5
Summary: ovos skill plugin
Home-page: https://github.com/OpenVoiceOS/skill-ovos-soundcloud
Author: JarbasAi
Author-email: jarbasai@mailfence.com
License: Apache-2.0
Keywords: ovos skill plugin
Platform: UNKNOWN
Requires-Dist: ovos-utils>=0.1.0
Requires-Dist: ovos-workshop>=0.0.16
Requires-Dist: nuvem-de-som
